django_wagtail_feeds-0.1.0.dist-info/METADATA
django_wagtail_feeds-0.1.0.dist-info/RECORD
django_wagtail_feeds-0.1.0.dist-info/WHEEL
django_wagtail_feeds-0.1.0.dist-info/top_level.txt
wagtail_feeds/__init__.py
wagtail_feeds/__init__.pyc
wagtail_feeds/admin.py
wagtail_feeds/feeds.py
wagtail_feeds/models.py
wagtail_feeds/views.py
wagtail_feeds/__pycache__/__init__.cpython-36.pyc
wagtail_feeds/locale/es/LC_MESSAGES/django.po
wagtail_feeds/locale/tr/LC_MESSAGES/django.po
wagtail_feeds/migrations/0001_initial.py
wagtail_feeds/migrations/0002_rssfeedssettings_feed_image_in_content.py
wagtail_feeds/migrations/0003_auto_20180130_0818.py
wagtail_feeds/migrations/0004_auto_20180130_0948.py
wagtail_feeds/migrations/0005_auto_20180130_1152.py
wagtail_feeds/migrations/0006_auto_20180216_0933.py
wagtail_feeds/migrations/0007_auto_20180216_1005.py
wagtail_feeds/migrations/__init__.py
