Metadata-Version: 2.1
Name: django-wagtail-feeds
Version: 0.1.0
Summary: Support RSS Feeds, Facebook Instant Articles and Apple News
Home-page: https://github.com/chrisdev/django-wagtail-feeds
Author: Christopher Clarke
Author-email: cclarke@chrisdev.com
License: MIT license
Keywords: wagtail_feeds
Platform: UNKNOWN
Classifier: Development Status :: 2 - Pre-Alpha
Classifier: Intended Audience :: Developers
Classifier: License :: OSI Approved :: MIT License
Classifier: Natural Language :: English
Classifier: Programming Language :: Python :: 2
Classifier: Programming Language :: Python :: 2.6
Classifier: Programming Language :: Python :: 2.7
Classifier: Programming Language :: Python :: 3
Classifier: Programming Language :: Python :: 3.3
Classifier: Programming Language :: Python :: 3.4
Classifier: Programming Language :: Python :: 3.5
Requires-Dist: Django (>=1.8)
Requires-Dist: Wagtail (>=1.8)
